{
  "locale": "nl",
  "title": "Weersverwachting",
  "width": 550,
  "topMargin": 50,
  "bottomMargin": 50,
  "rightMargin": 150,
  "legendPosition": { "x": 300, "y": 50 },
  "XExpandToGrid": true,
  "YWindowMinimum": 0,
  "YWindowMaximum": 100,
  "XAxes": [
    {
      "axisStyle": {
        "axisColor": null, 
        "labelColor": "63-63-63", 
        "markerColor": "200-200-200"
      }
    }
  ],
  "YAxes": [
    {
      "axisStyle": {
        "axisColor": null,
        "labelColor": "63-63-63",
        "markerColor": null
      },
      "unit": "%"
    }
  ],
  "graphDefaults": { 
    "type": "bar",
    "width": 15,
    "autoShift": true 
  },
  "graphs": {
    "Kans op zon": {
      "graphDrawStyle": {
        "colors": [ "15-63-255", "26-56-220" ]
      }
    },
    "Kans op neerslag": {
      "graphDrawStyle": {
        "colors": [ "30-128-240", "56-115-209" ]
      }
    }
  }
}